haikufy/__about__.py
haikufy/__init__.py
haikufy/app.py
haikufy/app.tcss
haikufy/converter.py
haikufy/entrypoints.py
haikufy-0.1.0.dist-info/METADATA
haikufy-0.1.0.dist-info/WHEEL
haikufy-0.1.0.dist-info/entry_points.txt
haikufy-0.1.0.dist-info/licenses/LICENSE.txt
haikufy-0.1.0.dist-info/RECORD
